LICENSE
README.md
setup.cfg
setup.py
deg/__init__.py
deg.egg-info/PKG-INFO
deg.egg-info/SOURCES.txt
deg.egg-info/dependency_links.txt
deg.egg-info/requires.txt
deg.egg-info/top_level.txt
deg.egg-info/zip-safe