Metadata-Version: 2.1
Name: deg
Version: 1.0.1
Summary: A Graph library to manage inheritance rules
Home-page: https://github.com/supratikchatterjee16/deg
Author: Supratik Chatterjee
Author-email: supratikdevm96@gmail.com
License:                                  Apache License
Keywords: graph,visualize,dependency,inheritance
Classifier: Programming Language :: Python :: 3
Classifier: Operating System :: OS Independent
License-File: LICENSE
